{
    "IsActive": true,
    "IsOmniScriptEmbeddable": false,
    "Name": "Create Case enrollee",
    "OmniProcessId": {
        "Name": "VHS_CreateCase",
        "VlocityDataPackType": "VlocityMatchingKeyObject",
        "VlocityMatchingRecordSourceKey": "OmniProcess/Case/Create/English",
        "VlocityRecordSObjectType": "OmniProcess"
    },
    "PropertySetConfig": {
        "HTMLTemplateId": "",
        "bundle": "VHSCreateCaseRecord",
        "businessCategory": "",
        "businessEvent": "",
        "controlWidth": 12,
        "enableActionMessage": false,
        "enableDefaultAbort": false,
        "errorMessage": {
            "custom": [
            ],
            "default": null
        },
        "failureAbortLabel": "Abort",
        "failureAbortMessage": "Are you sure?",
        "failureGoBackLabel": "Go Back",
        "failureNextLabel": "Continue",
        "inProgressMessage": "In Progress",
        "label": "Create Case enrollee",
        "message": {
        },
        "postMessage": "Done",
        "postTransformBundle": "",
        "pubsub": false,
        "redirectNextLabel": "Next",
        "redirectNextWidth": 3,
        "redirectPageName": "",
        "redirectPreviousLabel": "Previous",
        "redirectPreviousWidth": 3,
        "redirectTemplateUrl": "vlcAcknowledge.html",
        "remoteTimeout": 30000,
        "sendJSONNode": "",
        "sendJSONPath": "",
        "show": {
            "group": {
                "operator": "AND",
                "rules": [
                    {
                        "condition": "=",
                        "data": null,
                        "field": "CasePatient"
                    },
                    {
                        "condition": "<>",
                        "data": null,
                        "field": "PatientName"
                    },
                    {
                        "condition": "=",
                        "data": null,
                        "field": "PatientCase"
                    }
                ]
            }
        },
        "showPersistentComponent": [
            true,
            false
        ],
        "ssm": false,
        "validationRequired": "Submit",
        "wpm": false
    },
    "Type": "DataRaptor Post Action",
    "VlocityDataPackType": "SObject",
    "VlocityRecordSObjectType": "OmniProcessElement",
    "VlocityRecordSourceKey": "OmniProcessElement/OmniProcess/Case/Create/English/Create Case enrollee"
}